{"bltf35177b52b3f78ea":{"title":"Happy Hour","url":"/category/happy-hour","description":"","seo":{"title":"","description":"","keywords":""},"tags":[],"locale":"en-us","uid":"bltf35177b52b3f78ea","ACL":{},"_version":2,"_in_progress":false,"publish_details":[{"environment":"blte5c5941065c9eb52","locale":"en-us","time":"2021-04-15T07:21:20.379Z","user":"blt0bf2b07104b3c1e0","version":2},{"environment":"bltc2f04f9045507d1c","locale":"en-us","time":"2021-04-15T07:30:10.790Z","user":"blt42f2836554a56771","version":2}]},"blt8f90f6ed0e7d0cac":{"title":"Girl's Night","url":"/category/girl-s-night","description":"","seo":{"title":"","description":"","keywords":""},"tags":[],"locale":"en-us","uid":"blt8f90f6ed0e7d0cac","ACL":{},"_version":1,"_in_progress":false,"publish_details":[{"environment":"blte5c5941065c9eb52","locale":"en-us","time":"2021-04-15T07:11:49.883Z","user":"blt0bf2b07104b3c1e0","version":1},{"environment":"bltc2f04f9045507d1c","locale":"en-us","time":"2021-04-15T07:29:32.221Z","user":"blt42f2836554a56771","version":1}]},"blt6051aca0687db28d":{"title":"Boy's Night","url":"/category/boy-s-night","description":"","seo":{"title":"","description":"","keywords":""},"tags":[],"locale":"en-us","uid":"blt6051aca0687db28d","ACL":{},"_version":1,"_in_progress":false,"publish_details":[{"environment":"blte5c5941065c9eb52","locale":"en-us","time":"2021-04-15T07:11:36.961Z","user":"blt0bf2b07104b3c1e0","version":1},{"environment":"bltc2f04f9045507d1c","locale":"en-us","time":"2021-04-15T07:29:32.214Z","user":"blt42f2836554a56771","version":1}]},"bltc969c84ccb1fa38b":{"title":"BBQ","url":"/category/bbq","description":"","seo":{"title":"","description":"","keywords":""},"tags":[],"locale":"en-us","uid":"bltc969c84ccb1fa38b","ACL":{},"_version":1,"_in_progress":false,"publish_details":[{"environment":"blte5c5941065c9eb52","locale":"en-us","time":"2021-04-15T07:11:06.243Z","user":"blt0bf2b07104b3c1e0","version":1},{"environment":"bltc2f04f9045507d1c","locale":"en-us","time":"2021-04-15T07:29:00.994Z","user":"blt42f2836554a56771","version":1}]},"bltf51b81d797a7697c":{"title":"Dining","url":"/category/dining","description":"","seo":{"title":"","description":"","keywords":""},"tags":[],"locale":"en-us","uid":"bltf51b81d797a7697c","ACL":{},"_version":1,"_in_progress":false,"publish_details":[{"environment":"blte5c5941065c9eb52","locale":"en-us","time":"2021-04-15T07:10:20.910Z","user":"blt0bf2b07104b3c1e0","version":1}]},"bltfa458f075e32f5d4":{"title":"Toast","url":"/category/toast","description":"Celebration cocktails","seo":{"title":"","description":"","keywords":""},"tags":[],"locale":"en-us","uid":"bltfa458f075e32f5d4","ACL":{},"_version":2,"_in_progress":false,"publish_details":[{"environment":"blte5c5941065c9eb52","locale":"en-us","time":"2021-04-15T07:10:03.571Z","user":"blt0bf2b07104b3c1e0","version":2}]}}